remotv.py
remotv-0.0.2.dist-info/WHEEL
remotv-0.0.2.dist-info/METADATA
remotv-0.0.2.dist-info/RECORD
