Metadata-Version: 2.1
Name: remotv
Version: 0.0.2
Summary: More stuff coming
